inkpylib/__init__.py
inkpylib-0.0.1.dist-info/LICENSE
inkpylib-0.0.1.dist-info/METADATA
inkpylib-0.0.1.dist-info/WHEEL
inkpylib-0.0.1.dist-info/top_level.txt
inkpylib-0.0.1.dist-info/RECORD
